mockllm/__init__.py
mockllm/__main__.py
mockllm/cli.py
mockllm/config.py
mockllm/model_registry.py
mockllm/models.py
mockllm/provider_utils.py
mockllm/registry.py
mockllm/server.py
mockllm/utils.py
mockllm/providers/__init__.py
mockllm/providers/anthropic.py
mockllm/providers/base.py
mockllm/providers/example_custom.py
mockllm/providers/openai.py
mockllm-0.0.8.dist-info/METADATA
mockllm-0.0.8.dist-info/WHEEL
mockllm-0.0.8.dist-info/entry_points.txt
mockllm-0.0.8.dist-info/licenses/LICENSE
mockllm-0.0.8.dist-info/RECORD
