Metadata-Version: 2.4
Name: mockllm
Version: 0.0.8
Summary: A mock server that mimics OpenAI and Anthropic API formats for testing
Project-URL: Homepage, https://github.com/lukehinds/mockllm
Project-URL: Repository, https://github.com/lukehinds/mockllm
Author-email: Luke Hinds <luke@rdrocket.com>
License: Apache-2.0
License-File: LICENSE
Keywords: anthropic,llm,mock,openai,testing
Classifier: Development Status :: 4 - Beta
Classifier: Intended Audience :: Developers
Classifier: License :: OSI Approved :: Apache Software License
Classifier: Programming Language :: Python :: 3.10
Classifier: Programming Language :: Python :: 3.11
Classifier: Programming Language :: Python :: 3.12
Classifier: Topic :: Software Development :: Testing
Requires-Python: >=3.10
Requires-Dist: click>=8.1.0
Requires-Dist: fastapi>=0.68.0
Requires-Dist: httpx>=0.28.1
Requires-Dist: pydantic>=2.0.0
Requires-Dist: python-json-logger>=2.0.0
Requires-Dist: pyyaml>=5.4.1
Requires-Dist: tiktoken>=0.9.0
Requires-Dist: uvicorn>=0.15.0
Requires-Dist: watchdog>=2.1.0
Provides-Extra: dev
Requires-Dist: mypy>=0.900; extra == 'dev'
Requires-Dist: pytest-asyncio>=0.15.0; extra == 'dev'
Requires-Dist: pytest-mock>=3.10.0; extra == 'dev'
Requires-Dist: pytest>=6.0; extra == 'dev'
Requires-Dist: ruff>=0.1.0; extra == 'dev'
Requires-Dist: types-pyyaml>=6.0; extra == 'dev'
Provides-Extra: docs
Requires-Dist: mkdocs-material>=9.6.20; extra == 'docs'
Requires-Dist: mkdocs>=1.5.0; extra == 'docs'
Requires-Dist: mkdocstrings>=0.30.0; extra == 'docs'
Requires-Dist: mkdocstrings[python]>=0.24.0; extra == 'docs'
Requires-Dist: pymdown-extensions>=10.0; extra == 'docs'
